{
	"name": "Hôtel Métropole",
	"address": {
		"streetAddress": "31, place de Brouckère",
		"addressLocality": "Brussels, Belgium",
		"postalCode": "B-1000",
		"@type": "PostalAddress"
	},
	"geo": {
		"latitude": "50.85144",
		"longitude": "4.3537",
		"@type": "GeoCoordinates"
	},
	"event": {
		"startDate": "24 to 29 October 1927",
		"name": "Solvay Conference on Physics",
		"organizer": {
			"name": "International Solvay Institutes",
			"chairs": {
				"chair": [
					{
						"name": "Hendrik Lorentz"
					}
				],
				"@type": "Person"
			},
			"@type": "Organization"
		},
		"location": {
			"name": "Hôtel Métropole",
			"address": {
				"streetAddress": "Place De Brouckère 31",
				"addressLocality": "Brussels, Belgium",
				"postalCode": "B-1000",
				"@type": "PostalAddress"
			},
			"geo": {
				"latitude": "50.85144",
				"longitude": "4.3537",
				"@type": "GeoCoordinates"
			},
			"@type": "Place"
		},
		"@type": "Event"
	}
}